piplining.sv
// Stage 1: Calculate m = T[63:0] * N_INV
module reduction_stage1 (
    input  logic clk,
    input  logic [127:0] T,
    input  logic taken,
    output logic ready_in,
    output logic [127:0] T_out,
    output logic [63:0] m,
    output logic ready_out,
    input  logic given
);
    localparam logic [63:0] N_INV = 64'heeeeeeeeeeeeeeef;
    
    logic [127:0] T_reg = 128'd0; // added
    logic [63:0]  m_reg = 64'd0;  // added
    logic valid           = 1'b0; // added
    
    always_ff @(posedge clk) begin
        logic [127:0] m_tmp; // added
        if (taken) begin
            T_reg <= T;
            m_tmp = ({64'd0, T[63:0]} * {64'd0, N_INV}); // changed
            m_reg <= m_tmp[63:0];                       // changed
            valid <= 1'b1;
        end else if (given) begin
            valid <= 1'b0;
        end
    end
    
    assign T_out = T_reg;
    assign m = m_reg;
    assign ready_in = !valid || given;
    assign ready_out = valid;
endmodule


// Stage 2: Calculate t_full = T + (m * N)
module reduction_stage2 (
    input  logic clk,
    input  logic [127:0] T,
    input  logic [63:0] m,
    input  logic taken,
    output logic ready_in,
    output logic [128:0] t_full,     // changed
    output logic ready_out,
    input  logic given
);
    localparam logic [63:0] N = 64'hFFFFFFFFFFFFFFF1;
    
    logic [128:0] t_full_reg = 129'd0; // changed
    logic valid               = 1'b0;  // added
    
    always_ff @(posedge clk) begin
        if (taken) begin
            logic [127:0] prod; // added
            prod = ({64'd0, m} * {64'd0, N});           // changed
            t_full_reg <= {1'b0, T} + {1'b0, prod};     // changed
            valid <= 1'b1;
        end else if (given) begin
            valid <= 1'b0;
        end
    end
    
    assign t_full = t_full_reg;
    assign ready_in = !valid || given;
    assign ready_out = valid;
endmodule


// Stage 3: Calculate t[127:64] and final comparison
module reduction_stage3 (
    input  logic clk,
    input  logic [128:0] t_full, // changed
    input  logic taken,
    output logic ready_in,
    output logic [63:0] S,
    output logic ready_out,
    input  logic given
);
    localparam logic [63:0] N = 64'hFFFFFFFFFFFFFFF1;
    
    logic [63:0] S_reg = 64'd0; // added
    logic valid         = 1'b0; // added
    
    always_ff @(posedge clk) begin
        if (taken) begin
            logic [64:0] t;       // added
            logic [64:0] t_minus; // added
            
            t = t_full[128:64]; // changed
            if (t >= {1'b0, N}) begin
                t_minus = t - {1'b0, N}; // changed
                S_reg <= t_minus[63:0];  // changed
            end else begin
                S_reg <= t[63:0];        // changed
            end
            valid <= 1'b1;
        end else if (given) begin
            valid <= 1'b0;
        end
    end
    
    assign S = S_reg;
    assign ready_in = !valid || given;
    assign ready_out = valid;
endmodule


// reduction module connecting all 3 stages
module reduction (
    input  logic clk,
    input  logic [127:0] T,
    input  logic taken,
    output logic ready_in,
    output logic [63:0] S,
    output logic ready_out,
    input  logic given
);
    logic [127:0] T_stage1_out;
    logic [63:0]  m_stage1;
    logic ready_out_stage1, ready_in_stage2;
    logic taken_stage2, given_stage1;
    
    logic [128:0] t_full_stage2; // changed
    logic ready_out_stage2, ready_in_stage3;
    logic taken_stage3, given_stage2;
    
    reduction_stage1 u_stage1 (
        .clk(clk),
        .T(T),
        .taken(taken),
        .ready_in(ready_in),
        .T_out(T_stage1_out),
        .m(m_stage1),
        .ready_out(ready_out_stage1),
        .given(given_stage1)
    );
    
    assign taken_stage2 = ready_out_stage1 && ready_in_stage2;
    assign given_stage1 = taken_stage2;
    
    reduction_stage2 u_stage2 (
        .clk(clk),
        .T(T_stage1_out),
        .m(m_stage1),
        .taken(taken_stage2),
        .ready_in(ready_in_stage2),
        .t_full(t_full_stage2),
        .ready_out(ready_out_stage2),
        .given(given_stage2)
    );
    
    assign taken_stage3 = ready_out_stage2 && ready_in_stage3;
    assign given_stage2 = taken_stage3;
    
    reduction_stage3 u_stage3 (
        .clk(clk),
        .t_full(t_full_stage2),
        .taken(taken_stage3),
        .ready_in(ready_in_stage3),
        .S(S),
        .ready_out(ready_out),
        .given(given)
    );
endmodule


module montgomery_convert_in (
    input  logic        clk,
    input  logic [63:0] a,
    input  logic        taken,
    output logic        ready_in,
    output logic [63:0] a_bar,
    output logic        ready_out,
    input  logic        given
);
    localparam logic [63:0] R2 = 64'he1;

    logic [127:0] T = 128'd0;   // added
    logic valid_mult = 1'b0;     // added
    logic ready_redc_in;
    logic given_to_redc;

    always_ff @(posedge clk) begin
        if (taken) begin
            T <= ({64'd0, a} * {64'd0, R2}); // changed
            valid_mult <= 1'b1;
        end else if (given_to_redc) begin
            valid_mult <= 1'b0;
        end
    end

    assign ready_in = !valid_mult || ready_redc_in;
    assign given_to_redc = valid_mult && ready_redc_in;

    reduction u_redc (
        .clk(clk),
        .T(T),
        .taken(given_to_redc),
        .ready_in(ready_redc_in),
        .S(a_bar),
        .ready_out(ready_out),
        .given(given)
    );
endmodule


module montgomery_mul (
    input  logic        clk,
    input  logic [63:0] a_bar,
    input  logic [63:0] b_bar,
    input  logic        taken,
    output logic        ready_in,
    output logic [63:0] out_bar,
    output logic        ready_out,
    input  logic        given
);
    logic [127:0] T = 128'd0; // added
    logic valid_mult = 1'b0;  // added
    logic ready_redc_in;
    logic given_to_redc;

    always_ff @(posedge clk) begin
        if (taken) begin
            T <= ({64'd0, a_bar} * {64'd0, b_bar}); // changed
            valid_mult <= 1'b1;
        end else if (given_to_redc) begin
            valid_mult <= 1'b0;
        end
    end

    assign ready_in = !valid_mult || ready_redc_in;
    assign given_to_redc = valid_mult && ready_redc_in;

    reduction u_redc (
        .clk(clk),
        .T(T),
        .taken(given_to_redc),
        .ready_in(ready_redc_in),
        .S(out_bar),
        .ready_out(ready_out),
        .given(given)
    );
endmodule


module montgomery_convert_out (
    input  logic        clk,
    input  logic [63:0] a_bar,
    input  logic        taken,
    output logic        ready_in,
    output logic [63:0] a,
    output logic        ready_out,
    input  logic        given
);
    logic [127:0] T = 128'd0; // added
    logic valid_prep = 1'b0;  // added
    logic ready_redc_in;
    logic given_to_redc;

    always_ff @(posedge clk) begin
        if (taken) begin
            T <= {64'd0, a_bar};
            valid_prep <= 1'b1;
        end else if (given_to_redc) begin
            valid_prep <= 1'b0;
        end
    end

    assign ready_in = !valid_prep || ready_redc_in;
    assign given_to_redc = valid_prep && ready_redc_in;

    reduction u_redc (
        .clk(clk),
        .T(T),
        .taken(given_to_redc),
        .ready_in(ready_redc_in),
        .S(a),
        .ready_out(ready_out),
        .given(given)
    );
endmodule


module montgomery_top (
    input  logic        clk,
    input  logic [63:0] a,
    input  logic [63:0] b,
    input  logic        taken,
    output logic        ready_in,
    output logic [63:0] result,
    output logic        ready_out,
    input  logic        given
);
    logic [63:0] a_bar, b_bar, ab_bar;
    logic ready_in_a, ready_in_b, ready_in_mul, ready_in_out;
    logic ready_out_a, ready_out_b, ready_out_mul;
    logic taken_a, taken_b, taken_mul, taken_out;
    logic given_a, given_b, given_mul;
    
    logic [63:0] a_reg, b_reg;
    logic inputs_valid;

    always_ff @(posedge clk) begin
        if (taken) begin
            a_reg <= a;
            b_reg <= b;
            inputs_valid <= 1'b1;
        end else if (taken_a && taken_b) begin
            inputs_valid <= 1'b0;
        end
    end

    assign ready_in = !inputs_valid || (ready_in_a && ready_in_b);
    assign taken_a = inputs_valid && ready_in_a && ready_in_b;
    assign taken_b = taken_a;

    montgomery_convert_in u_in_a (
        .clk(clk), .a(a_reg), .taken(taken_a),
        .ready_in(ready_in_a), .a_bar(a_bar),
        .ready_out(ready_out_a), .given(given_a)
    );

    montgomery_convert_in u_in_b (
        .clk(clk), .a(b_reg), .taken(taken_b),
        .ready_in(ready_in_b), .a_bar(b_bar),
        .ready_out(ready_out_b), .given(given_b)
    );

    assign taken_mul = ready_out_a && ready_out_b && ready_in_mul;
    assign given_a = taken_mul;
    assign given_b = taken_mul;

    montgomery_mul u_mul (
        .clk(clk), .a_bar(a_bar), .b_bar(b_bar),
        .taken(taken_mul), .ready_in(ready_in_mul),
        .out_bar(ab_bar), .ready_out(ready_out_mul),
        .given(given_mul)
    );

    assign taken_out = ready_out_mul && ready_in_out;
    assign given_mul = taken_out;

    montgomery_convert_out u_out (
        .clk(clk), .a_bar(ab_bar), .taken(taken_out),
        .ready_in(ready_in_out), .a(result),
        .ready_out(ready_out), .given(given)
    );
endmodule

pipeline_tb.sv
`timescale 1ns/1ps

module tb_montgomery_pipelined;

    // -----------------------------
    // DUT interface (taken/given)
    // -----------------------------
    logic        clk;
    logic [63:0] a;
    logic [63:0] b;
    logic        taken;      // from TB -> DUT (we assert when we want to send and DUT is ready)
    logic        ready_in;   // from DUT -> TB (DUT can accept input)
    logic [63:0] result;     // from DUT -> TB
    logic        ready_out;  // from DUT -> TB (output valid)
    logic        given;      // from TB -> DUT (we accept output)

    // -----------------------------
    // Constants / reference
    // -----------------------------
    localparam logic [63:0] N = 64'hFFFFFFFFFFFFFFF1;

    // Queue of expected results (for pipelined / back-to-back)
    logic [63:0] exp_q[$];

    // -----------------------------
    // Instantiate DUT
    // -----------------------------
    montgomery_top dut (
        .clk      (clk),
        .a        (a),
        .b        (b),
        .taken    (taken),
        .ready_in (ready_in),
        .result   (result),
        .ready_out(ready_out),
        .given    (given)
    );

    // -----------------------------
    // Clock
    // -----------------------------
    initial begin
        clk = 1'b0;
        forever #5 clk = ~clk;
    end

    // -----------------------------
    // Helpers
    // -----------------------------
    function automatic logic [63:0] ref_modmul(input logic [63:0] aa, input logic [63:0] bb);
        logic [127:0] prod;
        logic [127:0] modv;
        begin
            prod = aa * bb;
            modv = prod % N;          // SystemVerilog supports % on packed vectors
            ref_modmul = modv[63:0];
        end
    endfunction

    // Drive one transaction using taken/ready_in handshake.
    // Holds a,b stable until accepted.
    task automatic send_tx(input logic [63:0] aa, input logic [63:0] bb);
        logic [63:0] exp;
        begin
            exp = ref_modmul(aa, bb);
            exp_q.push_back(exp);

            // Present inputs
            a <= aa;
            b <= bb;

            // Wait until DUT is ready, then pulse taken for 1 cycle
            @(posedge clk);
            while (!ready_in) @(posedge clk);

            taken <= 1'b1;
            @(posedge clk);
            taken <= 1'b0;

            // After accept, inputs can change next cycle; we leave them as-is or overwrite later
        end
    endtask

    // -----------------------------
    // Output consumption + checking
    // -----------------------------
    // Always ready to take output (no backpressure from TB)
    initial begin
        given = 1'b1;
    end

    // Check whenever DUT says output is ready
    always_ff @(posedge clk) begin
        if (ready_out) begin
            if (exp_q.size() == 0) begin
                $fatal(1, "[%0t] DUT produced an output but TB has no expected value queued!", $time);
            end else begin
                logic [63:0] exp;
                exp = exp_q.pop_front();

                if (result !== exp) begin
                    $display("[%0t] MISMATCH!", $time);
                    $display("  got : 0x%016h", result);
                    $display("  exp : 0x%016h", exp);
                    $fatal(1, "Stopping due to mismatch.");
                end else begin
                    $display("[%0t] PASS  result=0x%016h", $time, result);
                end
            end
        end
    end

    // -----------------------------
    // Waveform
    // -----------------------------
    initial begin
        $dumpfile("montgomery_pipelined.vcd");
        $dumpvars(0, tb_montgomery_pipelined);
    end

    // -----------------------------
    // Stimulus
    // -----------------------------
    initial begin
        // Init
        a = '0;
        b = '0;
        taken = 1'b0;

        // Let unknowns settle a bit
        repeat (5) @(posedge clk);

        $display("Time\tready_in\ttaken\tready_out\tgiven\tA\t\t\tB\t\t\tresult");
        $monitor("%0t\t%b\t\t%b\t%b\t\t%b\t%016h\t%016h\t%016h",
                 $time, ready_in, taken, ready_out, given, a, b, result);

        // ---- Test 1
        $display("\nTest 1: a=5, b=7");
        send_tx(64'h5, 64'h7);

        // ---- Test 2
        $display("\nTest 2: a=A, b=F");
        send_tx(64'hA, 64'hF);

        // ---- Test 3: back-to-back (pipelining)
        $display("\nTest 3: back-to-back transactions");

        send_tx(64'h3, 64'h4);  // added
        send_tx(64'h6, 64'h8);  // added


        // Add a few more random-ish tests
        $display("\nTest 4+: a few more values");
        send_tx(64'h0000_0000_0000_0001, 64'h0000_0000_0000_0001);
        send_tx(64'h0000_0000_0000_0002, 64'h0000_0000_0000_0003);
        send_tx(64'h1234_5678_9ABC_DEF0, 64'h0FED_CBA9_8765_4321);
        send_tx(64'hFFFF_FFFF_FFFF_FFFE, 64'h0000_0000_0000_0002);

        // Wait until all expected results drained
        while (exp_q.size() != 0) @(posedge clk);

        // Extra cycles to be safe
        repeat (10) @(posedge clk);

        $display("\nSimulation complete: all tests passed.");
        $finish;
    end

endmodule

montgomery_pipelined.vcd
$date
	Sun Feb 08 22:40:35 2026
$end
$version
	Icarus Verilog
$end
$timescale
	1ps
$end
$scope module tb_montgomery_pipelined $end
$var wire 64 ! result [63:0] $end
$var wire 1 " ready_out $end
$var wire 1 # ready_in $end
$var parameter 64 $ N $end
$var reg 64 % a [63:0] $end
$var reg 64 & b [63:0] $end
$var reg 1 ' clk $end
$var reg 1 ( given $end
$var reg 1 ) taken $end
$scope function ref_modmul $end
$upscope $end
$scope module dut $end
$var wire 64 * a [63:0] $end
$var wire 64 + b [63:0] $end
$var wire 1 ' clk $end
$var wire 1 ( given $end
$var wire 1 , given_a $end
$var wire 1 - given_b $end
$var wire 1 . given_mul $end
$var wire 1 # ready_in $end
$var wire 1 ) taken $end
$var wire 1 / taken_a $end
$var wire 1 0 taken_b $end
$var wire 1 1 taken_mul $end
$var wire 1 2 taken_out $end
$var wire 64 3 result [63:0] $end
$var wire 1 4 ready_out_mul $end
$var wire 1 5 ready_out_b $end
$var wire 1 6 ready_out_a $end
$var wire 1 " ready_out $end
$var wire 1 7 ready_in_out $end
$var wire 1 8 ready_in_mul $end
$var wire 1 9 ready_in_b $end
$var wire 1 : ready_in_a $end
$var wire 64 ; b_bar [63:0] $end
$var wire 64 < ab_bar [63:0] $end
$var wire 64 = a_bar [63:0] $end
$var reg 64 > a_reg [63:0] $end
$var reg 64 ? b_reg [63:0] $end
$var reg 1 @ inputs_valid $end
$scope module u_in_a $end
$var wire 64 A a [63:0] $end
$var wire 1 ' clk $end
$var wire 1 , given $end
$var wire 1 B given_to_redc $end
$var wire 1 : ready_in $end
$var wire 1 / taken $end
$var wire 1 C ready_redc_in $end
$var wire 1 6 ready_out $end
$var wire 64 D a_bar [63:0] $end
$var parameter 64 E R2 $end
$var reg 128 F T [127:0] $end
$var reg 1 G valid_mult $end
$scope module u_redc $end
$var wire 128 H T [127:0] $end
$var wire 1 ' clk $end
$var wire 1 , given $end
$var wire 1 I given_stage1 $end
$var wire 1 J given_stage2 $end
$var wire 1 B taken $end
$var wire 1 K taken_stage2 $end
$var wire 1 L taken_stage3 $end
$var wire 129 M t_full_stage2 [128:0] $end
$var wire 1 N ready_out_stage2 $end
$var wire 1 O ready_out_stage1 $end
$var wire 1 6 ready_out $end
$var wire 1 P ready_in_stage3 $end
$var wire 1 Q ready_in_stage2 $end
$var wire 1 C ready_in $end
$var wire 64 R m_stage1 [63:0] $end
$var wire 128 S T_stage1_out [127:0] $end
$var wire 64 T S [63:0] $end
$scope module u_stage1 $end
$var wire 128 U T [127:0] $end
$var wire 128 V T_out [127:0] $end
$var wire 1 ' clk $end
$var wire 1 I given $end
$var wire 64 W m [63:0] $end
$var wire 1 C ready_in $end
$var wire 1 O ready_out $end
$var wire 1 B taken $end
$var parameter 64 X N_INV $end
$var reg 128 Y T_reg [127:0] $end
$var reg 64 Z m_reg [63:0] $end
$var reg 1 [ valid $end
$scope begin $unm_blk_1 $end
$var reg 128 \ m_tmp [127:0] $end
$upscope $end
$upscope $end
$scope module u_stage2 $end
$var wire 128 ] T [127:0] $end
$var wire 1 ' clk $end
$var wire 1 J given $end
$var wire 64 ^ m [63:0] $end
$var wire 1 Q ready_in $end
$var wire 1 N ready_out $end
$var wire 129 _ t_full [128:0] $end
$var wire 1 K taken $end
$var parameter 64 ` N $end
$var reg 129 a t_full_reg [128:0] $end
$var reg 1 b valid $end
$scope begin $unm_blk_5 $end
$var reg 128 c prod [127:0] $end
$upscope $end
$upscope $end
$scope module u_stage3 $end
$var wire 64 d S [63:0] $end
$var wire 1 ' clk $end
$var wire 1 , given $end
$var wire 1 P ready_in $end
$var wire 1 6 ready_out $end
$var wire 129 e t_full [128:0] $end
$var wire 1 L taken $end
$var parameter 64 f N $end
$var reg 64 g S_reg [63:0] $end
$var reg 1 h valid $end
$scope begin $unm_blk_8 $end
$var reg 65 i t [64:0] $end
$var reg 65 j t_minus [64:0] $end
$upscope $end
$upscope $end
$upscope $end
$upscope $end
$scope module u_in_b $end
$var wire 64 k a [63:0] $end
$var wire 1 ' clk $end
$var wire 1 - given $end
$var wire 1 l given_to_redc $end
$var wire 1 9 ready_in $end
$var wire 1 0 taken $end
$var wire 1 m ready_redc_in $end
$var wire 1 5 ready_out $end
$var wire 64 n a_bar [63:0] $end
$var parameter 64 o R2 $end
$var reg 128 p T [127:0] $end
$var reg 1 q valid_mult $end
$scope module u_redc $end
$var wire 128 r T [127:0] $end
$var wire 1 ' clk $end
$var wire 1 - given $end
$var wire 1 s given_stage1 $end
$var wire 1 t given_stage2 $end
$var wire 1 l taken $end
$var wire 1 u taken_stage2 $end
$var wire 1 v taken_stage3 $end
$var wire 129 w t_full_stage2 [128:0] $end
$var wire 1 x ready_out_stage2 $end
$var wire 1 y ready_out_stage1 $end
$var wire 1 5 ready_out $end
$var wire 1 z ready_in_stage3 $end
$var wire 1 { ready_in_stage2 $end
$var wire 1 m ready_in $end
$var wire 64 | m_stage1 [63:0] $end
$var wire 128 } T_stage1_out [127:0] $end
$var wire 64 ~ S [63:0] $end
$scope module u_stage1 $end
$var wire 128 !" T [127:0] $end
$var wire 128 "" T_out [127:0] $end
$var wire 1 ' clk $end
$var wire 1 s given $end
$var wire 64 #" m [63:0] $end
$var wire 1 m ready_in $end
$var wire 1 y ready_out $end
$var wire 1 l taken $end
$var parameter 64 $" N_INV $end
$var reg 128 %" T_reg [127:0] $end
$var reg 64 &" m_reg [63:0] $end
$var reg 1 '" valid $end
$scope begin $unm_blk_1 $end
$var reg 128 (" m_tmp [127:0] $end
$upscope $end
$upscope $end
$scope module u_stage2 $end
$var wire 128 )" T [127:0] $end
$var wire 1 ' clk $end
$var wire 1 t given $end
$var wire 64 *" m [63:0] $end
$var wire 1 { ready_in $end
$var wire 1 x ready_out $end
$var wire 129 +" t_full [128:0] $end
$var wire 1 u taken $end
$var parameter 64 ," N $end
$var reg 129 -" t_full_reg [128:0] $end
$var reg 1 ." valid $end
$scope begin $unm_blk_5 $end
$var reg 128 /" prod [127:0] $end
$upscope $end
$upscope $end
$scope module u_stage3 $end
$var wire 64 0" S [63:0] $end
$var wire 1 ' clk $end
$var wire 1 - given $end
$var wire 1 z ready_in $end
$var wire 1 5 ready_out $end
$var wire 129 1" t_full [128:0] $end
$var wire 1 v taken $end
$var parameter 64 2" N $end
$var reg 64 3" S_reg [63:0] $end
$var reg 1 4" valid $end
$scope begin $unm_blk_8 $end
$var reg 65 5" t [64:0] $end
$var reg 65 6" t_minus [64:0] $end
$upscope $end
$upscope $end
$upscope $end
$upscope $end
$scope module u_mul $end
$var wire 64 7" a_bar [63:0] $end
$var wire 64 8" b_bar [63:0] $end
$var wire 1 ' clk $end
$var wire 1 . given $end
$var wire 1 9" given_to_redc $end
$var wire 1 8 ready_in $end
$var wire 1 1 taken $end
$var wire 1 :" ready_redc_in $end
$var wire 1 4 ready_out $end
$var wire 64 ;" out_bar [63:0] $end
$var reg 128 <" T [127:0] $end
$var reg 1 =" valid_mult $end
$scope module u_redc $end
$var wire 128 >" T [127:0] $end
$var wire 1 ' clk $end
$var wire 1 . given $end
$var wire 1 ?" given_stage1 $end
$var wire 1 @" given_stage2 $end
$var wire 1 9" taken $end
$var wire 1 A" taken_stage2 $end
$var wire 1 B" taken_stage3 $end
$var wire 129 C" t_full_stage2 [128:0] $end
$var wire 1 D" ready_out_stage2 $end
$var wire 1 E" ready_out_stage1 $end
$var wire 1 4 ready_out $end
$var wire 1 F" ready_in_stage3 $end
$var wire 1 G" ready_in_stage2 $end
$var wire 1 :" ready_in $end
$var wire 64 H" m_stage1 [63:0] $end
$var wire 128 I" T_stage1_out [127:0] $end
$var wire 64 J" S [63:0] $end
$scope module u_stage1 $end
$var wire 128 K" T [127:0] $end
$var wire 128 L" T_out [127:0] $end
$var wire 1 ' clk $end
$var wire 1 ?" given $end
$var wire 64 M" m [63:0] $end
$var wire 1 :" ready_in $end
$var wire 1 E" ready_out $end
$var wire 1 9" taken $end
$var parameter 64 N" N_INV $end
$var reg 128 O" T_reg [127:0] $end
$var reg 64 P" m_reg [63:0] $end
$var reg 1 Q" valid $end
$scope begin $unm_blk_1 $end
$var reg 128 R" m_tmp [127:0] $end
$upscope $end
$upscope $end
$scope module u_stage2 $end
$var wire 128 S" T [127:0] $end
$var wire 1 ' clk $end
$var wire 1 @" given $end
$var wire 64 T" m [63:0] $end
$var wire 1 G" ready_in $end
$var wire 1 D" ready_out $end
$var wire 129 U" t_full [128:0] $end
$var wire 1 A" taken $end
$var parameter 64 V" N $end
$var reg 129 W" t_full_reg [128:0] $end
$var reg 1 X" valid $end
$scope begin $unm_blk_5 $end
$var reg 128 Y" prod [127:0] $end
$upscope $end
$upscope $end
$scope module u_stage3 $end
$var wire 64 Z" S [63:0] $end
$var wire 1 ' clk $end
$var wire 1 . given $end
$var wire 1 F" ready_in $end
$var wire 1 4 ready_out $end
$var wire 129 [" t_full [128:0] $end
$var wire 1 B" taken $end
$var parameter 64 \" N $end
$var reg 64 ]" S_reg [63:0] $end
$var reg 1 ^" valid $end
$scope begin $unm_blk_8 $end
$var reg 65 _" t [64:0] $end
$var reg 65 `" t_minus [64:0] $end
$upscope $end
$upscope $end
$upscope $end
$upscope $end
$scope module u_out $end
$var wire 64 a" a_bar [63:0] $end
$var wire 1 ' clk $end
$var wire 1 ( given $end
$var wire 1 b" given_to_redc $end
$var wire 1 7 ready_in $end
$var wire 1 2 taken $end
$var wire 1 c" ready_redc_in $end
$var wire 1 " ready_out $end
$var wire 64 d" a [63:0] $end
$var reg 128 e" T [127:0] $end
$var reg 1 f" valid_prep $end
$scope module u_redc $end
$var wire 128 g" T [127:0] $end
$var wire 1 ' clk $end
$var wire 1 ( given $end
$var wire 1 h" given_stage1 $end
$var wire 1 i" given_stage2 $end
$var wire 1 b" taken $end
$var wire 1 j" taken_stage2 $end
$var wire 1 k" taken_stage3 $end
$var wire 129 l" t_full_stage2 [128:0] $end
$var wire 1 m" ready_out_stage2 $end
$var wire 1 n" ready_out_stage1 $end
$var wire 1 " ready_out $end
$var wire 1 o" ready_in_stage3 $end
$var wire 1 p" ready_in_stage2 $end
$var wire 1 c" ready_in $end
$var wire 64 q" m_stage1 [63:0] $end
$var wire 128 r" T_stage1_out [127:0] $end
$var wire 64 s" S [63:0] $end
$scope module u_stage1 $end
$var wire 128 t" T [127:0] $end
$var wire 128 u" T_out [127:0] $end
$var wire 1 ' clk $end
$var wire 1 h" given $end
$var wire 64 v" m [63:0] $end
$var wire 1 c" ready_in $end
$var wire 1 n" ready_out $end
$var wire 1 b" taken $end
$var parameter 64 w" N_INV $end
$var reg 128 x" T_reg [127:0] $end
$var reg 64 y" m_reg [63:0] $end
$var reg 1 z" valid $end
$scope begin $unm_blk_1 $end
$var reg 128 {" m_tmp [127:0] $end
$upscope $end
$upscope $end
$scope module u_stage2 $end
$var wire 128 |" T [127:0] $end
$var wire 1 ' clk $end
$var wire 1 i" given $end
$var wire 64 }" m [63:0] $end
$var wire 1 p" ready_in $end
$var wire 1 m" ready_out $end
$var wire 129 ~" t_full [128:0] $end
$var wire 1 j" taken $end
$var parameter 64 !# N $end
$var reg 129 "# t_full_reg [128:0] $end
$var reg 1 ## valid $end
$scope begin $unm_blk_5 $end
$var reg 128 $# prod [127:0] $end
$upscope $end
$upscope $end
$scope module u_stage3 $end
$var wire 64 %# S [63:0] $end
$var wire 1 ' clk $end
$var wire 1 ( given $end
$var wire 1 o" ready_in $end
$var wire 1 " ready_out $end
$var wire 129 &# t_full [128:0] $end
$var wire 1 k" taken $end
$var parameter 64 '# N $end
$var reg 64 (# S_reg [63:0] $end
$var reg 1 )# valid $end
$scope begin $unm_blk_8 $end
$var reg 65 *# t [64:0] $end
$var reg 65 +# t_minus [64:0] $end
$upscope $end
$upscope $end
$upscope $end
$upscope $end
$upscope $end
$scope begin $unm_blk_31 $end
$var reg 64 ,# exp [63:0] $end
$upscope $end
$scope task send_tx $end
$upscope $end
$upscope $end
$enddefinitions $end
$comment Show the parameter values. $end
$dumpall
b1111111111111111111111111111111111111111111111111111111111110001 '#
b1111111111111111111111111111111111111111111111111111111111110001 !#
b1110111011101110111011101110111011101110111011101110111011101111 w"
b1111111111111111111111111111111111111111111111111111111111110001 \"
b1111111111111111111111111111111111111111111111111111111111110001 V"
b1110111011101110111011101110111011101110111011101110111011101111 N"
b1111111111111111111111111111111111111111111111111111111111110001 2"
b1111111111111111111111111111111111111111111111111111111111110001 ,"
b1110111011101110111011101110111011101110111011101110111011101111 $"
b11100001 o
b1111111111111111111111111111111111111111111111111111111111110001 f
b1111111111111111111111111111111111111111111111111111111111110001 `
b1110111011101110111011101110111011101110111011101110111011101111 X
b11100001 E
b1111111111111111111111111111111111111111111111111111111111110001 $
$end
#0
$dumpvars
bx ,#
bx +#
bx *#
0)#
b0 (#
b0 &#
b0 %#
bx $#
0##
b0 "#
b0 ~"
b0 }"
b0 |"
bx {"
0z"
b0 y"
b0 x"
b0 v"
b0 u"
b0 t"
b0 s"
b0 r"
b0 q"
1p"
1o"
0n"
0m"
b0 l"
0k"
0j"
0i"
0h"
b0 g"
0f"
b0 e"
b0 d"
1c"
0b"
b0 a"
bx `"
bx _"
0^"
b0 ]"
b0 ["
b0 Z"
bx Y"
0X"
b0 W"
b0 U"
b0 T"
b0 S"
bx R"
0Q"
b0 P"
b0 O"
b0 M"
b0 L"
b0 K"
b0 J"
b0 I"
b0 H"
1G"
1F"
0E"
0D"
b0 C"
0B"
0A"
0@"
0?"
b0 >"
0="
b0 <"
b0 ;"
1:"
09"
b0 8"
b0 7"
bx 6"
bx 5"
04"
b0 3"
b0 1"
b0 0"
bx /"
0."
b0 -"
b0 +"
b0 *"
b0 )"
bx ("
0'"
b0 &"
b0 %"
b0 #"
b0 ""
b0 !"
b0 ~
b0 }
b0 |
1{
1z
0y
0x
b0 w
0v
0u
0t
0s
b0 r
0q
b0 p
b0 n
1m
0l
bx k
bx j
bx i
0h
b0 g
b0 e
b0 d
bx c
0b
b0 a
b0 _
b0 ^
b0 ]
bx \
0[
b0 Z
b0 Y
b0 W
b0 V
b0 U
b0 T
b0 S
b0 R
1Q
1P
0O
0N
b0 M
0L
0K
0J
0I
b0 H
0G
b0 F
b0 D
1C
0B
bx A
x@
bx ?
bx >
b0 =
b0 <
b0 ;
1:
19
18
17
06
05
04
b0 3
02
01
x0
x/
0.
0-
0,
b0 +
b0 *
0)
1(
0'
b0 &
b0 %
1#
0"
b0 !
$end
#5000
1'
#10000
0'
#15000
1'
#20000
0'
#25000
1'
#30000
0'
#35000
1'
#40000
0'
#45000
b111 &
b111 +
b101 %
b101 *
1'
#50000
0'
#55000
1)
1'
#60000
0'
#65000
10
1/
b1111 &
b1111 +
b1010 %
b1010 *
0)
1@
b111 ?
b111 k
b101 >
b101 A
1'
#70000
0'
#75000
00
0/
1l
1B
0@
1q
b11000100111 p
b11000100111 r
b11000100111 !"
1G
b10001100101 F
b10001100101 H
b10001100101 U
1)
1'
#80000
0'
#85000
10
1/
1s
1u
1I
1K
0B
0l
1y
1'"
b1101001 |
b1101001 #"
b1101001 *"
b1101001 &"
b11000100111 }
b11000100111 ""
b11000100111 )"
b11000100111 %"
1O
1[
b1001011 R
b1001011 W
b1001011 ^
b1001011 Z
b10001100101 S
b10001100101 V
b10001100101 ]
b10001100101 Y
b100 &
b100 +
b11 %
b11 *
0)
0G
0q
1@
b1111 ?
b1111 k
b1010 >
b1010 A
b101101111100000000000000000000000000000000000000000000000000000000001101001 ("
b100000110100000000000000000000000000000000000000000000000000000000001001011 \
1'
#90000
0'
#95000
00
0/
0s
0u
0I
0K
1J
1L
1t
1v
1l
1B
0y
0'"
0O
0[
1N
1b
b10010110000000000000000000000000000000000000000000000000000000000000000 M
b10010110000000000000000000000000000000000000000000000000000000000000000 _
b10010110000000000000000000000000000000000000000000000000000000000000000 e
b10010110000000000000000000000000000000000000000000000000000000000000000 a
1x
1."
b11010010000000000000000000000000000000000000000000000000000000000000000 w
b11010010000000000000000000000000000000000000000000000000000000000000000 +"
b11010010000000000000000000000000000000000000000000000000000000000000000 1"
b11010010000000000000000000000000000000000000000000000000000000000000000 -"
0@
1q
b110100101111 p
b110100101111 r
b110100101111 !"
1G
b100011001010 F
b100011001010 H
b100011001010 U
1)
b10010101111111111111111111111111111111111111111111111111111101110011011 c
b11010001111111111111111111111111111111111111111111111111111100111011001 /"
1'
#100000
0'
#105000
1,
1-
11
10
1/
1s
1u
1I
1K
1z
1P
0B
0l
0t
0v
0J
0L
1y
1'"
b11100001 |
b11100001 #"
b11100001 *"
b11100001 &"
b110100101111 }
b110100101111 ""
b110100101111 )"
b110100101111 %"
1O
1[
b10010110 R
b10010110 W
b10010110 ^
b10010110 Z
b100011001010 S
b100011001010 V
b100011001010 ]
b100011001010 Y
15
14"
b1101001 ;
b1101001 n
b1101001 ~
b1101001 0"
b1101001 8"
b1101001 3"
16
1h
b1001011 =
b1001011 D
b1001011 T
b1001011 d
b1001011 7"
b1001011 g
b1000 &
b1000 +
b110 %
b110 *
0)
0G
0q
1@
b100 ?
b100 k
b11 >
b11 A
0x
0."
0N
0b
b1100010011100000000000000000000000000000000000000000000000000000000011100001 ("
b1000001101000000000000000000000000000000000000000000000000000000000010010110 \
b1101001 5"
b1001011 i
1'
#110000
0'
