HTMMM/htmmm_naf_v2.sv
module multiply #(
    parameter N = 4
)(
    input  logic             clk,
    input  logic [N+1:0]     a,
    input  logic [N+1:0]     b,
    output logic [2*N+1:0]   T,
    output logic [N+1:0]     T_L,
    output logic [N-1:0]     T_H
);
    logic [2*N+1:0] product;

    always_comb begin
        product = a * b;
    end

    always_ff @(posedge clk) begin
        T   <= product;
        T_L <= product[N+1:0];
        T_H <= product[2*N+1 : N+2];
    end
endmodule


// NLTM : NAF Low-part Truncated Multiplication
// Low-part truncation: only keep bits [N+1:0] of each product
// D = R - T_L = ~T_L + 1  (used later by NFHTM for error compensation)
module NLTM #(
    parameter N = 4,
    // NAF positive part of M'
    parameter [N+1:0] M_INV_POS  = 6'b010000,   // example: +16
    // NAF negative part of M'
    parameter [N+1:0] M_INV_NEG  = 6'b000001    // example: -1  => M'=15
)(
    input  logic         clk,
    input  logic [N+1:0] T_L,
    output logic [N+1:0] Q_L,
    output logic [N+1:0] D
);
    // accumulators for low-part truncated multiplication
    logic [N+2:0] pos_acc;   // one extra guard bit for borrowing
    logic [N+2:0] neg_acc;

    always_comb begin
        pos_acc = '0;
        neg_acc = '0;

        // Low-part truncated multiply: T_L * M_INV_POS
        // For each set bit in M_INV_POS, shift T_L left and accumulate
        // Only keep lower N+2 bits (truncation happens naturally by register width)
        for (int i = 0; i <= N+1; i++) begin
            if (M_INV_POS[i])
                pos_acc = pos_acc + (({1'b0, T_L} << i) & {{1{1'b0}}, {N+2{1'b1}}});
        end

        for (int i = 0; i <= N+1; i++) begin
            if (M_INV_NEG[i])
                neg_acc = neg_acc + (({1'b0, T_L} << i) & {{1{1'b0}}, {N+2{1'b1}}});
        end
    end

    always_ff @(posedge clk) begin
        Q_L <= ({1'b1, pos_acc[N+1:0]} - {1'b0, neg_acc[N+1:0]});
        // D = R - T_L
        D   <= (~T_L) + 1'b1;
    end
endmodule


// NFHTM : NAF High-Part Truncated Multiplication
// U = Q_L ⋉_(N) Mpos  -  Q_L ⋉_(N) Mneg
//   dcal  = U[d-1:0]            (bottom d bits of U, the CEP region)
//   dreal = D[N+1 : N+2-d]      (top d bits of D)
//   Carry  condition: dcal[d-1]=1, dreal[d-1]=0, dcal[d-2:0] > dreal[d-2:0]  => S_H = U + 1
//   Borrow condition: dcal[d-1]=0, dreal[d-1]=1, dcal[d-2:0] < dreal[d-2:0]  => S_H = U - 1
//   Otherwise:                                                               => S_H = U
module NFHTM #(
    parameter N                 = 4,
    parameter d                 = 3,
    // NAF positive part of M
    parameter [N+1:0] M_POS     = 6'b010000,    // example: Mpos=16
    // NAF negative part of M
    parameter [N+1:0] M_NEG     = 6'b000001     // example: Mneg=1 => M=15
)(
    input  logic         clk,
    input  logic [N+1:0] Q_L,
    input  logic [N+1:0] D,
    output logic [N-1:0] S_H
);
    // Accumulators for high-part truncated multiplication
    // We need N+d bits: upper N bits are the MSP answer, lower d bits are CEP (dcal)
    logic [N+d-1:0] pos_acc;
    logic [N+d-1:0] neg_acc;
    logic [N+d-1:0] U_full;   // U = pos_acc - neg_acc

    logic [d-1:0]   d_cal;
    logic [d-1:0]   d_real;
    logic [N-1:0]   U_msp;    // upper N bits = MSP candidate answer

    always_comb begin
        pos_acc = '0;   // N+d bits wide
        neg_acc = '0;

        for (int i = 0; i <= N+1; i++) begin
            if (M_POS[i]) begin
                for (int j = 0; j <= N+1; j++) begin
                    int pos = j + i;
                    // only accumulate if this lands in MSP+CEP window [2N+3 : N+4-d]
                    if (pos >= (N+2-d)) begin
                        pos_acc[pos - (N+2-d)] += Q_L[j];
                    end
                end
            end
        end

        for (int i = 0; i <= N+1; i++) begin
            if (M_NEG[i]) begin
                for (int j = 0; j <= N+1; j++) begin
                    int pos = j + i;
                    if (pos >= (N+2-d)) begin
                        neg_acc[pos - (N+2-d)] += Q_L[j];
                    end
                end
            end
        end

        U_full = pos_acc - neg_acc;

        // CEP = bottom d bits of accumulator (positions [N+3 : N+4-d] of full product)
        d_cal  = U_full[d-1 : 0];

        // dreal from D
        d_real = D[N+1 -: d];

        // MSP = upper N bits of accumulator (positions [2N+3 : N+4] of full product)
        U_msp  = U_full[N+d-1 : d];
    end

    always_ff @(posedge clk) begin
        // Algorithm 4, steps 4-9
        // Carry:  dcal[d-1]=1, dreal[d-1]=0, dcal[d-2:0] > dreal[d-2:0]
        if (d_cal[d-1] & ~d_real[d-1] & (d_cal[d-2:0] > d_real[d-2:0]))
            S_H <= U_msp + 1'b1;

        // Borrow: dcal[d-1]=0, dreal[d-1]=1, dcal[d-2:0] < dreal[d-2:0]
        else if (~d_cal[d-1] & d_real[d-1] & (d_cal[d-2:0] < d_real[d-2:0]))
            S_H <= U_msp - 1'b1;

        // No error
        else
            S_H <= U_msp;
    end

endmodule

module final_result_opt #(
    parameter N = 4
)(
    input  logic         clk,
    input  logic [N-1:0] T_H,
    input  logic [N-1:0] S_H,
    input  logic         tl_zero,   // 1 when T_L == 0, pipelined from stage 1
    output logic [N:0]   C
);
    always_ff @(posedge clk) begin
        if (tl_zero)
            // T_L=0 => S_H=0 and carry=0 => C = T_H
            C <= {1'b0, T_H};
        else
            // T_L!=0 => carry always 1 => C = T_H + S_H + 1
            C <= {1'b0, T_H} + {1'b0, S_H} + 1'b1;
    end
endmodule

module top_HTMMM_NAF #(
    parameter N                  = 4,
    parameter d                  = 3,
    // NAF of M
    parameter [N+1:0] M_POS      = 6'b010000,   // Mpos
    parameter [N+1:0] M_NEG      = 6'b000001,   // Mneg  (M = Mpos - Mneg = 15)
    // NAF of M' = -M^{-1} mod R
    parameter [N+1:0] M_INV_POS  = 6'b010000,   // M'pos  (set correctly for your prime)
    parameter [N+1:0] M_INV_NEG  = 6'b000001    // M'neg
)(
    input  logic       clk,
    input  logic [N-1:0] A,          // 0 <= A < 2M
    input  logic [N-1:0] B,          // 0 <= B < 2M
    output logic [N-1:0] C           // A*B*R^{-1} mod M
);

    logic [2*N+1:0] T_full;
    logic [N+1:0]   T_L_s1;
    logic [N-1:0]   T_H_s1;
    logic           tl_zero_s1;    // 1 when T_L == 0

    multiply #(.N(N)) u_mul (
        .clk (clk),
        .a   ({1'b0, A}),
        .b   ({1'b0, B}),
        .T   (T_full),
        .T_L (T_L_s1),
        .T_H (T_H_s1)
    );

    // Register the zero flag in the same FF stage as multiply output
    // product[N+1:0] is T_L before it is registered inside multiply,
    // so we check the combinational product directly here
    logic [2*N+1:0] product_comb;
    assign product_comb = ({1'b0, A}) * ({1'b0, B});

    always_ff @(posedge clk) begin
        // Flag is 1 when the lower N+2 bits of the product are all zero
        tl_zero_s1 <= (product_comb[N+1:0] == '0);
    end

   
    logic [N+1:0] Q_L_s2, D_s2;
    logic [N-1:0] T_H_s2;
    logic         tl_zero_s2;

    always_ff @(posedge clk) begin
        T_H_s2     <= T_H_s1;
        tl_zero_s2 <= tl_zero_s1;
    end

    NLTM #(
        .N         (N),
        .M_INV_POS (M_INV_POS),
        .M_INV_NEG (M_INV_NEG)
    ) u_nltm (
        .clk (clk),
        .T_L (T_L_s1),
        .Q_L (Q_L_s2),
        .D   (D_s2)
    );

 
    logic [N-1:0] S_H_s3;
    logic [N-1:0] T_H_s3;
    logic         tl_zero_s3;

    always_ff @(posedge clk) begin
        T_H_s3     <= T_H_s2;
        tl_zero_s3 <= tl_zero_s2;
    end

    NFHTM #(
        .N     (N),
        .d     (d),
        .M_POS (M_POS),
        .M_NEG (M_NEG)
    ) u_nfhtm (
        .clk (clk),
        .Q_L (Q_L_s2),
        .D   (D_s2),
        .S_H (S_H_s3)
    );

 
    //   tl_zero=1  =>  C = T_H          (S_H=0, carry=0, bypass addition)
    //   tl_zero=0  =>  C = T_H + S_H + 1 (carry always 1 when T_L != 0)
   
    final_result_opt #(.N(N)) u_final (
        .clk    (clk),
        .T_H    (T_H_s3),
        .S_H    (S_H_s3),
        .tl_zero(tl_zero_s3),
        .C      (C)
    );

endmodule

HTMMM/htmmm_tb.sv
`timescale 1ns/1ps

module htmmm_tb;

    // Parameters matching top_HTMMM_NAF defaults
    parameter N = 4;
    parameter d = 3;
    parameter [N+1:0] M_POS     = 6'b010000;
    parameter [N+1:0] M_NEG     = 6'b000001;
    parameter [N+1:0] M_INV_POS = 6'b010000;
    parameter [N+1:0] M_INV_NEG = 6'b000001;

    // DUT signals
    logic           clk;
    logic [N-1:0]   A, B;
    logic [N-1:0]   C;   // NOTE: top declares output [N:0] C inside final_result_opt
                         // but top port is [N-1:0] C — match exactly

    // Instantiate DUT
    top_HTMMM_NAF #(
        .N         (N),
        .d         (d),
        .M_POS     (M_POS),
        .M_NEG     (M_NEG),
        .M_INV_POS (M_INV_POS),
        .M_INV_NEG (M_INV_NEG)
    ) dut (
        .clk (clk),
        .A   (A),
        .B   (B),
        .C   (C)
    );

    // Clock: 10 ns period
    initial clk = 0;
    always #5 clk = ~clk;

    // VCD dump
    initial begin
        $dumpfile("htmmm.vcd");
        $dumpvars(0, htmmm_tb);
    end

    // Stimulus
    // Pipeline is 4 stages deep (multiply -> NLTM -> NFHTM -> final_result_opt)
    // so outputs appear 4 cycles after input
    integer i, j;
    initial begin
        A = 0; B = 0;
        @(posedge clk); #1;

        // Sweep a few input combinations
        for (i = 0; i < 2**N; i = i + 1) begin
            for (j = 0; j < 2**N; j = j + 1) begin
                A = i[N-1:0];
                B = j[N-1:0];
                repeat (10) @(posedge clk) #1;
            end
        end

        // Flush pipeline (4 extra cycles)
        repeat (4) @(posedge clk);

        $display("Simulation done. C final = %0d", C);
        $finish;
    end

    // Monitor output
    initial begin
        $monitor("t=%0t | A=%0d B=%0d | C=%0d", $time, A, B, C);
    end

endmodule

HTMMM/htmmm.vcd
$date
	Tue Mar 10 16:21:38 2026
$end
$version
	Icarus Verilog
$end
$timescale
	1ps
$end
$scope module htmmm_tb $end
$var wire 4 ! C [3:0] $end
$var parameter 6 " M_INV_NEG $end
$var parameter 6 # M_INV_POS $end
$var parameter 6 $ M_NEG $end
$var parameter 6 % M_POS $end
$var parameter 32 & N $end
$var parameter 32 ' d $end
$var reg 4 ( A [3:0] $end
$var reg 4 ) B [3:0] $end
$var reg 1 * clk $end
$var integer 32 + i [31:0] $end
$var integer 32 , j [31:0] $end
$scope module dut $end
$var wire 4 - A [3:0] $end
$var wire 4 . B [3:0] $end
$var wire 1 * clk $end
$var wire 10 / product_comb [9:0] $end
$var wire 10 0 T_full [9:0] $end
$var wire 6 1 T_L_s1 [5:0] $end
$var wire 4 2 T_H_s1 [3:0] $end
$var wire 4 3 S_H_s3 [3:0] $end
$var wire 6 4 Q_L_s2 [5:0] $end
$var wire 6 5 D_s2 [5:0] $end
$var wire 4 6 C [3:0] $end
$var parameter 6 7 M_INV_NEG $end
$var parameter 6 8 M_INV_POS $end
$var parameter 6 9 M_NEG $end
$var parameter 6 : M_POS $end
$var parameter 32 ; N $end
$var parameter 32 < d $end
$var reg 4 = T_H_s2 [3:0] $end
$var reg 4 > T_H_s3 [3:0] $end
$var reg 1 ? tl_zero_s1 $end
$var reg 1 @ tl_zero_s2 $end
$var reg 1 A tl_zero_s3 $end
$scope module u_final $end
$var wire 4 B T_H [3:0] $end
$var wire 1 * clk $end
$var wire 1 A tl_zero $end
$var wire 4 C S_H [3:0] $end
$var parameter 32 D N $end
$var reg 5 E C [4:0] $end
$upscope $end
$scope module u_mul $end
$var wire 6 F a [5:0] $end
$var wire 6 G b [5:0] $end
$var wire 1 * clk $end
$var parameter 32 H N $end
$var reg 10 I T [9:0] $end
$var reg 4 J T_H [3:0] $end
$var reg 6 K T_L [5:0] $end
$var reg 10 L product [9:0] $end
$upscope $end
$scope module u_nfhtm $end
$var wire 1 * clk $end
$var wire 6 M Q_L [5:0] $end
$var wire 6 N D [5:0] $end
$var parameter 6 O M_NEG $end
$var parameter 6 P M_POS $end
$var parameter 32 Q N $end
$var parameter 32 R d $end
$var reg 4 S S_H [3:0] $end
$var reg 7 T U_full [6:0] $end
$var reg 4 U U_msp [3:0] $end
$var reg 3 V d_cal [2:0] $end
$var reg 3 W d_real [2:0] $end
$var reg 7 X neg_acc [6:0] $end
$var reg 7 Y pos_acc [6:0] $end
$scope begin $ivl_for_loop2 $end
$var integer 32 Z i [31:0] $end
$scope begin $ivl_for_loop3 $end
$var integer 32 [ j [31:0] $end
$scope begin $unm_blk_10 $end
$var integer 32 \ pos [31:0] $end
$upscope $end
$upscope $end
$upscope $end
$scope begin $ivl_for_loop4 $end
$var integer 32 ] i [31:0] $end
$scope begin $ivl_for_loop5 $end
$var integer 32 ^ j [31:0] $end
$scope begin $unm_blk_14 $end
$var integer 32 _ pos [31:0] $end
$upscope $end
$upscope $end
$upscope $end
$upscope $end
$scope module u_nltm $end
$var wire 6 ` T_L [5:0] $end
$var wire 1 * clk $end
$var parameter 6 a M_INV_NEG $end
$var parameter 6 b M_INV_POS $end
$var parameter 32 c N $end
$var reg 6 d D [5:0] $end
$var reg 6 e Q_L [5:0] $end
$var reg 7 f neg_acc [6:0] $end
$var reg 7 g pos_acc [6:0] $end
$scope begin $ivl_for_loop0 $end
$var integer 32 h i [31:0] $end
$upscope $end
$scope begin $ivl_for_loop1 $end
$var integer 32 i i [31:0] $end
$upscope $end
$upscope $end
$upscope $end
$upscope $end
$enddefinitions $end
$comment Show the parameter values. $end
$dumpall
b100 c
b10000 b
b1 a
b11 R
b100 Q
b10000 P
b1 O
b100 H
b100 D
b11 <
b100 ;
b10000 :
b1 9
b10000 8
b1 7
b11 '
b100 &
b10000 %
b1 $
b10000 #
b1 "
$end
#0
$dumpvars
b110 i
b110 h
bx g
bx f
bx e
bx d
bx `
b0 _
b110 ^
b110 ]
b0 \
b110 [
b110 Z
b0 Y
b0 X
bx W
b0 V
b0 U
b0 T
bx S
bx N
bx M
b0 L
bx K
bx J
bx I
b0 G
b0 F
bx E
bx C
bx B
xA
x@
x?
bx >
bx =
bx 6
bx 5
bx 4
bx 3
bx 2
bx 1
bx 0
b0 /
b0 .
b0 -
bx ,
bx +
0*
b0 )
b0 (
bx !
$end
#5000
b110 i
b110 h
b0 f
b0 g
b0 2
b0 J
b0 1
b0 K
b0 `
b0 0
b0 I
b0 3
b0 C
b0 S
1?
1*
#6000
b0 ,
b0 +
#10000
0*
#15000
b0 W
b110 ^
b110 ]
b110 [
b110 Z
1@
b0 =
b0 5
b0 N
b0 d
b0 4
b0 M
b0 e
1*
#20000
0*
#25000
1A
b0 >
b0 B
1*
#30000
0*
#35000
b0 !
b0 6
b0 E
1*
#40000
0*
#45000
1*
#50000
0*
#55000
1*
#60000
0*
#65000
1*
#70000
0*
#75000
1*
#80000
0*
#85000
1*
#90000
0*
#95000
1*
#100000
0*
#105000
1*
#106000
b1 G
b1 )
b1 .
b1 ,
#110000
0*
#115000
1*
#120000
0*
#125000
1*
#130000
0*
#135000
1*
#140000
0*
#145000
1*
#150000
0*
#155000
1*
#160000
0*
#165000
1*
#170000
0*
#175000
1*
#180000
0*
#185000
1*
#190000
0*
#195000
1*
#200000
0*
#205000
1*
#206000
b10 G
b10 )
b10 .
b10 ,
#210000
0*
#215000
1*
#220000
0*
#225000
1*
#230000
0*
#235000
1*
#240000
0*
#245000
1*
#250000
0*
#255000
1*
#260000
0*
#265000
1*
#270000
0*
#275000
1*
#280000
0*
#285000
1*
#290000
0*
#295000
1*
#300000
0*
#305000
1*
#306000
b11 G
b11 )
b11 .
b11 ,
#310000
0*
#315000
1*
#320000
0*
#325000
1*
#330000
0*
#335000
1*
#340000
0*
#345000
1*
#350000
0*
#355000
1*
#360000
0*
#365000
1*
#370000
0*
#375000
1*
#380000
0*
#385000
1*
#390000
0*
#395000
1*
#400000
0*
#405000
1*
#406000
b100 G
b100 )
b100 .
b100 ,
#410000
0*
#415000
1*
#420000
0*
#425000
1*
#430000
0*
#435000
1*
#440000
0*
#445000
1*
#450000
0*
#455000
1*
#460000
0*
#465000
1*
#470000
0*
#475000
1*
#480000
0*
#485000
1*
#490000
0*
#495000
1*
#500000
0*
#505000
1*
#506000
b101 G
b101 )
b101 .
b101 ,
#510000
0*
#515000
1*
#520000
0*
#525000
1*
#530000
0*
#535000
1*
#540000
0*
#545000
1*
#550000
0*
#555000
1*
#560000
0*
#565000
1*
#570000
0*
#575000
1*
#580000
0*
#585000
1*
#590000
0*
#595000
1*
#600000
0*
#605000
1*
#606000
b110 G
b110 )
b110 .
b110 ,
#610000
0*
#615000
1*
#620000
0*
#625000
1*
#630000
0*
#635000
1*
#640000
0*
#645000
1*
#650000
0*
#655000
1*
#660000
0*
#665000
1*
#670000
0*
#675000
1*
#680000
0*
#685000
1*
#690000
0*
#695000
1*
#700000
0*
#705000
1*
#706000
b111 G
b111 )
b111 .
b111 ,
#710000
0*
#715000
1*
#720000
0*
#725000
1*
#730000
0*
#735000
1*
#740000
0*
#745000
1*
#750000
0*
#755000
1*
#760000
0*
#765000
1*
#770000
0*
#775000
1*
#780000
0*
#785000
1*
#790000
0*
#795000
1*
#800000
0*
#805000
1*
#806000
b1000 G
b1000 )
b1000 .
b1000 ,
#810000
0*
#815000
1*
#820000
0*
#825000
1*
#830000
0*
#835000
1*
#840000
0*
#845000
1*
#850000
0*
#855000
1*
#860000
0*
#865000
1*
#870000
0*
#875000
1*
#880000
0*
#885000
1*
#890000
0*
#895000
1*
#900000
0*
#905000
1*
#906000
b1001 G
b1001 )
b1001 .
b1001 ,
#910000
0*
#915000
1*
#920000
0*
#925000
1*
#930000
0*
#935000
1*
#940000
0*
#945000
1*
#950000
0*
#955000
1*
#960000
0*
#965000
1*
#970000
0*
#975000
1*
#980000
0*
#985000
1*
#990000
0*
#995000
1*
#1000000
0*
#1005000
1*
#1006000
b1010 G
b1010 )
b1010 .
b1010 ,
#1010000
0*
#1015000
1*
#1020000
0*
#1025000
1*
#1030000
0*
#1035000
1*
#1040000
0*
#1045000
1*
#1050000
0*
#1055000
1*
#1060000
0*
#1065000
1*
#1070000
0*
#1075000
1*
#1080000
0*
#1085000
1*
#1090000
0*
#1095000
1*
#1100000
0*
#1105000
1*
#1106000
b1011 G
b1011 )
b1011 .
b1011 ,
#1110000
0*
#1115000
1*
#1120000
0*
#1125000
1*
#1130000
0*
#1135000
1*
#1140000
0*
#1145000
1*
#1150000
0*
#1155000
1*
#1160000
0*
#1165000
1*
#1170000
0*
#1175000
1*
#1180000
0*
#1185000
1*
#1190000
0*
#1195000
1*
#1200000
0*
#1205000
1*
#1206000
b1100 G
b1100 )
b1100 .
b1100 ,
#1210000
0*
#1215000
1*
#1220000
0*
#1225000
1*
#1230000
0*
#1235000
1*
#1240000
0*
#1245000
1*
#1250000
0*
#1255000
1*
#1260000
0*
#1265000
1*
#1270000
0*
#1275000
1*
#1280000
0*
#1285000
1*
#1290000
0*
#1295000
1*
#1300000
0*
#1305000
1*
#1306000
b1101 G
b1101 )
b1101 .
b1101 ,
#1310000
0*
#1315000
1*
#1320000
0*
#1325000
1*
#1330000
0*
#1335000
1*
#1340000
0*
#1345000
1*
#1350000
0*
#1355000
1*
#1360000
0*
#1365000
1*
#1370000
0*
#1375000
1*
#1380000
0*
#1385000
1*
#1390000
0*
#1395000
1*
#1400000
0*
#1405000
1*
#1406000
b1110 G
b1110 )
b1110 .
b1110 ,
#1410000
0*
#1415000
1*
#1420000
0*
#1425000
1*
#1430000
0*
#1435000
1*
#1440000
0*
#1445000
1*
#1450000
0*
#1455000
1*
#1460000
0*
#1465000
1*
#1470000
0*
#1475000
1*
#1480000
0*
#1485000
1*
#1490000
0*
#1495000
1*
#1500000
0*
#1505000
1*
#1506000
b1111 G
b1111 )
b1111 .
b1111 ,
#1510000
0*
#1515000
1*
#1520000
0*
#1525000
1*
#1530000
0*
#1535000
1*
#1540000
0*
#1545000
1*
#1550000
0*
#1555000
1*
#1560000
0*
#1565000
1*
#1570000
0*
#1575000
1*
#1580000
0*
#1585000
1*
#1590000
0*
#1595000
1*
#1600000
0*
#1605000
1*
#1606000
b0 G
b0 )
b0 .
b1 F
b0 /
b1 (
b1 -
b1 +
b0 ,
#1610000
0*
#1615000
1*
#1620000
0*
#1625000
1*
#1630000
0*
#1635000
1*
#1640000
0*
#1645000
1*
#1650000
0*
#1655000
1*
#1660000
0*
#1665000
1*
#1670000
0*
#1675000
1*
#1680000
0*
#1685000
1*
#1690000
0*
#1695000
1*
#1700000
0*
#1705000
1*
#1706000
b1 L
b1 G
b1 /
b1 )
b1 .
b1 ,
#1710000
0*
#1715000
b1 f
b110 i
b10000 g
b110 h
0?
b1 1
b1 K
b1 `
b1 0
b1 I
1*
#1720000
0*
#1725000
b111 W
b110 ^
b110 ]
b110 [
b110 Z
b111111 5
b111111 N
b111111 d
b1111 4
b1111 M
b1111 e
0@
1*
#1730000
0*
#1735000
0A
b1111 3
b1111 C
b1111 S
1*
#1740000
0*
#1745000
b10000 E
1*
#1750000
0*
#1755000
1*
#1760000
0*
#1765000
1*
#1770000
0*
#1775000
1*
#1780000
0*
#1785000
1*
#1790000
0*
#1795000
1*
#1800000
0*
#1805000
1*
#1806000
b10 L
b10 G
b10 /
b10 )
b10 .
b10 ,
#1810000
0*
#1815000
b110 i
b110 h
b10 f
b100000 g
b10 1
b10 K
b10 `
b10 0
b10 I
1*
#1820000
0*
#1825000
b110 ^
b110 ]
b110 [
b110 Z
b111110 5
b111110 N
b111110 d
b11110 4
b11110 M
b11110 e
1*
#1830000
0*
#1835000
1*
#1840000
0*
#1845000
1*
#1850000
0*
#1855000
1*
#1860000
0*
#1865000
1*
#1870000
0*
#1875000
1*
#1880000
0*
#1885000
1*
#1890000
0*
#1895000
1*
#1900000
0*
#1905000
1*
#1906000
b11 L
b11 G
b11 /
b11 )
b11 .
b11 ,
#1910000
0*
#1915000
b110 i
b110 h
b11 f
b110000 g
b11 1
b11 K
b11 `
b11 0
b11 I
1*
#1920000
0*
#1925000
b110 ^
b110 ]
b110 [
b110 Z
b111101 5
b111101 N
b111101 d
b101101 4
b101101 M
b101101 e
1*
#1930000
0*
#1935000
1*
#1940000
0*
#1945000
1*
#1950000
0*
#1955000
1*
#1960000
0*
#1965000
1*
#1970000
0*
#1975000
1*
#1980000
0*
#1985000
1*
#1990000
0*
#1995000
1*
#2000000
0*
#2005000
1*
#2006000
b100 L
b100 G
b100 /
b100 )
b100 .
b100 ,
#2010000
0*
#2015000
b110 i
b110 h
b100 f
b0 g
b100 1
b100 K
b100 `
b100 0
b100 I
1*
#2020000
0*
#2025000
b110 ^
b110 ]
b110 [
b110 Z
b111100 5
b111100 N
b111100 d
b111100 4
b111100 M
b111100 e
1*
#2030000
0*
#2035000
1*
#2040000
0*
#2045000
1*
#2050000
0*
#2055000
1*
#2060000
0*
#2065000
1*
#2070000
0*
#2075000
1*
#2080000
0*
#2085000
1*
#2090000
0*
#2095000
1*
#2100000
0*
#2105000
1*
#2106000
b101 L
b101 G
b101 /
b101 )
b101 .
b101 ,
#2110000
0*
#2115000
b110 i
b10000 g
b110 h
b101 f
b101 1
b101 K
b101 `
b101 0
b101 I
1*
#2120000
0*
#2125000
b110 ^
b110 ]
b110 [
b110 Z
b111011 5
b111011 N
b111011 d
b1011 4
b1011 M
b1011 e
1*
#2130000
0*
#2135000
1*
#2140000
0*
#2145000
1*
#2150000
0*
#2155000
1*
#2160000
0*
#2165000
1*
#2170000
0*
#2175000
1*
#2180000
0*
#2185000
1*
#2190000
0*
#2195000
1*
#2200000
0*
#2205000
1*
#2206000
b110 L
b110 G
b110 /
b110 )
b110 .
b110 ,
#2210000
0*
#2215000
b110 i
b110 h
b110 f
b100000 g
b110 1
b110 K
b110 `
b110 0
b110 I
1*
#2220000
0*
#2225000
b110 ^
b110 ]
b110 [
b110 Z
b111010 5
b111010 N
b111010 d
b11010 4
b11010 M
b11010 e
1*
#2230000
0*
#2235000
1*
#2240000
0*
#2245000
1*
#2250000
0*
#2255000
1*
#2260000
0*
#2265000
1*
#2270000
0*
#2275000
1*
#2280000
0*
#2285000
1*
#2290000
0*
#2295000
1*
#2300000
0*
#2305000
1*
#2306000
b111 L
b111 G
b111 /
b111 )
b111 .
b111 ,
#2310000
0*
#2315000
b110 i
b110 h
b111 f
b110000 g
b111 1
b111 K
b111 `
b111 0
b111 I
1*
#2320000
0*
#2325000
b110 ^
b110 ]
b110 [
b110 Z
b111001 5
b111001 N
b111001 d
b101001 4
b101001 M
b101001 e
1*
#2330000
0*
#2335000
1*
#2340000
0*
#2345000
1*
#2350000
0*
#2355000
1*
#2360000
0*
#2365000
1*
#2370000
0*
#2375000
1*
#2380000
0*
#2385000
1*
#2390000
0*
#2395000
1*
#2400000
0*
#2405000
1*
#2406000
b1000 L
b1000 G
b1000 /
b1000 )
b1000 .
b1000 ,
#2410000
0*
#2415000
b110 i
b110 h
b1000 f
b0 g
b1000 1
b1000 K
b1000 `
b1000 0
b1000 I
1*
#2420000
0*
#2425000
b110 ^
b110 ]
b110 [
b110 Z
b111000 5
b111000 N
b111000 d
b111000 4
b111000 M
b111000 e
1*
#2430000
0*
#2435000
1*
#2440000
0*
#2445000
1*
#2450000
0*
#2455000
1*
#2460000
0*
#2465000
1*
#2470000
0*
#2475000
1*
#2480000
0*
#2485000
1*
#2490000
0*
#2495000
1*
#2500000
0*
#2505000
1*
#2506000
b1001 L
b1001 G
b1001 /
b1001 )
b1001 .
b1001 ,
#2510000
0*
#2515000
b110 i
b10000 g
b110 h
b1001 f
b1001 1
b1001 K
b1001 `
b1001 0
b1001 I
1*
#2520000
0*
#2525000
b110 W
b110 ^
b110 ]
b110 [
b110 Z
b110111 5
b110111 N
b110111 d
b111 4
b111 M
b111 e
1*
#2530000
0*
#2535000
1*
#2540000
0*
#2545000
1*
#2550000
0*
#2555000
1*
#2560000
0*
#2565000
1*
#2570000
0*
#2575000
1*
#2580000
0*
#2585000
1*
#2590000
0*
#2595000
1*
#2600000
0*
#2605000
1*
#2606000
b1010 L
b1010 G
b1010 /
b1010 )
b1010 .
b1010 ,
#2610000
0*
#2615000
b110 i
b110 h
b1010 f
b100000 g
b1010 1
b1010 K
b1010 `
b1010 0
b1010 I
1*
#2620000
0*
#2625000
b110 ^
b110 ]
b110 [
b110 Z
b110110 5
b110110 N
b110110 d
b10110 4
b10110 M
b10110 e
1*
#2630000
0*
#2635000
1*
#2640000
0*
#2645000
1*
#2650000
0*
#2655000
1*
#2660000
0*
#2665000
1*
#2670000
0*
#2675000
1*
#2680000
0*
#2685000
1*
#2690000
0*
#2695000
1*
#2700000
0*
#2705000
1*
#2706000
b1011 L
b1011 G
b1011 /
b1011 )
b1011 .
b1011 ,
#2710000
0*
#2715000
b110 i
b110 h
b1011 f
b110000 g
b1011 1
b1011 K
b1011 `
b1011 0
b1011 I
1*
#2720000
0*
#2725000
b110 ^
b110 ]
b110 [
b110 Z
b110101 5
b110101 N
b110101 d
b100101 4
b100101 M
b100101 e
1*
#2730000
0*
#2735000
1*
#2740000
0*
#2745000
1*
#2750000
0*
#2755000
1*
#2760000
0*
#2765000
1*
#2770000
0*
#2775000
1*
#2780000
0*
#2785000
1*
#2790000
0*
#2795000
1*
#2800000
0*
#2805000
1*
#2806000
b1100 L
b1100 G
b1100 /
b1100 )
b1100 .
b1100 ,
#2810000
0*
#2815000
b110 i
b110 h
b1100 f
b0 g
b1100 1
b1100 K
b1100 `
b1100 0
b1100 I
1*
#2820000
0*
#2825000
b110 ^
b110 ]
b110 [
b110 Z
b110100 5
b110100 N
b110100 d
b110100 4
b110100 M
b110100 e
1*
#2830000
0*
#2835000
1*
#2840000
0*
#2845000
1*
#2850000
0*
#2855000
1*
#2860000
0*
#2865000
1*
#2870000
0*
#2875000
1*
#2880000
0*
#2885000
1*
#2890000
0*
#2895000
1*
#2900000
0*
#2905000
1*
#2906000
b1101 L
b1101 G
b1101 /
b1101 )
b1101 .
b1101 ,
#2910000
0*
#2915000
b110 i
b10000 g
b110 h
b1101 f
b1101 1
b1101 K
b1101 `
b1101 0
b1101 I
1*
#2920000
0*
#2925000
b110 ^
b110 ]
b110 [
b110 Z
b110011 5
b110011 N
b110011 d
b11 4
b11 M
b11 e
1*
#2930000
0*
#2935000
1*
#2940000
0*
#2945000
1*
#2950000
0*
#2955000
1*
#2960000
0*
#2965000
1*
#2970000
0*
#2975000
1*
#2980000
0*
#2985000
1*
#2990000
0*
#2995000
1*
#3000000
0*
#3005000
1*
#3006000
b1110 L
b1110 G
b1110 /
b1110 )
b1110 .
b1110 ,
#3010000
0*
#3015000
b110 i
b110 h
b1110 f
b100000 g
b1110 1
b1110 K
b1110 `
b1110 0
b1110 I
1*
#3020000
0*
#3025000
b110 ^
b110 ]
b110 [
b110 Z
b110010 5
b110010 N
b110010 d
b10010 4
b10010 M
b10010 e
1*
#3030000
0*
#3035000
1*
#3040000
0*
#3045000
1*
#3050000
0*
#3055000
1*
#3060000
0*
#3065000
1*
#3070000
0*
#3075000
1*
#3080000
0*
#3085000
1*
#3090000
0*
#3095000
1*
#3100000
0*
#3105000
1*
#3106000
b1111 L
b1111 G
b1111 /
b1111 )
b1111 .
b1111 ,
#3110000
0*
#3115000
b110 i
b110 h
b1111 f
b110000 g
b1111 1
b1111 K
b1111 `
b1111 0
b1111 I
1*
#3120000
0*
#3125000
b110 ^
b110 ]
b110 [
b110 Z
b110001 5
b110001 N
b110001 d
b100001 4
b100001 M
b100001 e
1*
#3130000
0*
#3135000
1*
#3140000
0*
#3145000
1*
#3150000
0*
#3155000
1*
#3160000
0*
#3165000
1*
#3170000
0*
#3175000
1*
#3180000
0*
#3185000
1*
#3190000
0*
#3195000
1*
#3200000
0*
#3205000
1*
#3206000
b0 L
b0 G
b0 )
b0 .
b10 F
b0 /
b10 (
b10 -
b10 +
b0 ,
#3210000
0*
